QRComponent41C/__init__.py
QRComponent41C/main.py
QRComponent41C-0.0.24.dist-info/METADATA
QRComponent41C-0.0.24.dist-info/WHEEL
QRComponent41C-0.0.24.dist-info/top_level.txt
QRComponent41C-0.0.24.dist-info/RECORD
